livechain/__init__.py
livechain/graph/__init__.py
livechain/graph/constants.py
livechain/graph/context.py
livechain/graph/cron.py
livechain/graph/emitter.py
livechain/graph/executor.py
livechain/graph/ops.py
livechain/graph/types.py
livechain/graph/utils.py
livechain/graph/func/__init__.py
livechain/graph/func/nodes.py
livechain/graph/func/root.py
livechain/graph/func/routine.py
livechain/graph/func/utils.py
livechain/graph/persist/__init__.py
livechain/graph/persist/base.py
livechain/graph/persist/local.py
livechain-0.1.0.dist-info/METADATA
livechain-0.1.0.dist-info/WHEEL
livechain-0.1.0.dist-info/licenses/LICENSE
livechain-0.1.0.dist-info/RECORD
