Metadata-Version: 2.4
Name: livechain
Version: 0.1.0
Summary: A framework for building reactive realtime AI agents with LiveKit, LangGraph, and LangChain
Project-URL: Documentation, https://github.com/toubatbrian/livechain
Project-URL: Source, https://github.com/toubatbrian/livechain
Project-URL: Bug Tracker, https://github.com/toubatbrian/livechain/issues
Author-email: Brian Yin <toubatbrian@gmail.com>
License: MIT
License-File: LICENSE
Keywords: agent,ai,langchain,langgraph,llm,realtime
Classifier: Development Status :: 3 - Alpha
Classifier: Intended Audience :: Developers
Classifier: License :: OSI Approved :: MIT License
Classifier: Programming Language :: Python :: 3
Classifier: Programming Language :: Python :: 3.12
Classifier: Topic :: Software Development :: Libraries :: Python Modules
Requires-Python: ~=3.12
Requires-Dist: langchain-core
Requires-Dist: langchain-openai
Requires-Dist: langgraph
Requires-Dist: livekit-agents
Requires-Dist: livekit-plugins-deepgram
Requires-Dist: livekit-plugins-openai
Requires-Dist: livekit-plugins-silero
Requires-Dist: livekit-plugins-turn-detector
Requires-Dist: python-dotenv
Provides-Extra: dev
Requires-Dist: black>=24.3.0; extra == 'dev'
Requires-Dist: ipykernel>=6.29.5; extra == 'dev'
Requires-Dist: isort>=5.13.2; extra == 'dev'
Requires-Dist: mypy>=1.9.0; extra == 'dev'
Requires-Dist: pytest-asyncio>=0.25.3; extra == 'dev'
Requires-Dist: pytest-xdist>=3.6.1; extra == 'dev'
Requires-Dist: pytest>=8.3.5; extra == 'dev'
Requires-Dist: ruff>=0.3.7; extra == 'dev'
